{"cod":"200","calctime":0.1053,"cnt":9,"list":[{"id":2965140,"name":"Cork","coord":{"lon":-8.47061,"lat":51.897968},"main":{"temp":0,"pressure":994,"temp_min":0,"temp_max":0,"humidity":100},"dt":1479679853,"wind":{"speed":7.2,"deg":10},"clouds":{"all":20},"weather":[{"id":801,"main":"Clouds","description":"few clouds","icon":"02n"}]},{"id":2964574,"name":"Dublin","coord":{"lon":-6.26719,"lat":53.34399},"main":{"temp":-1.58,"pressure":996,"humidity":100,"temp_min":-2,"temp_max":-1},"dt":1479679796,"wind":{"speed":2.6,"deg":280,"var_beg":260,"var_end":320},"clouds":{"all":75},"weather":[{"id":741,"main":"Fog","description":"fog","icon":"50n"}]},{"id":2643734,"name":"Londonderry County Borough","coord":{"lon":-7.30917,"lat":54.997211},"main":{"temp":4.71,"temp_min":4.705,"temp_max":4.705,"pressure":1005.26,"sea_level":1012.73,"grnd_level":1005.26,"humidity":96},"dt":1479683096,"wind":{"speed":4.96,"deg":33},"clouds":{"all":0},"weather":[{"id":800,"main":"Clear","description":"Sky is Clear","icon":"01n"}]},{"id":2640194,"name":"Plymouth","coord":{"lon":-4.14305,"lat":50.371529},"main":{"temp":6,"pressure":992,"humidity":87,"temp_min":6,"temp_max":6},"dt":1479679848,"wind":{"speed":5.7,"deg":50},"clouds":{"all":40},"weather":[{"id":500,"main":"Rain","description":"light rain","icon":"10n"}]},{"id":2648579,"name":"Glasgow","coord":{"lon":-4.25763,"lat":55.86515},"main":{"temp":0.31,"pressure":998,"humidity":86,"temp_min":0,"temp_max":1},"dt":1479679849,"wind":{"speed":1,"deg":0},"clouds":{"all":90},"weather":[{"id":804,"main":"Clouds","description":"overcast clouds","icon":"04n"}]},{"id":2643741,"name":"City of London","coord":{"lon":-0.09184,"lat":51.512791},"main":{"temp":4.76,"pressure":996,"humidity":87,"temp_min":4,"temp_max":6},"dt":1479679848,"wind":{"speed":3.6,"deg":80},"clouds":{"all":75},"weather":[{"id":501,"main":"Rain","description":"moderate rain","icon":"10n"},{"id":701,"main":"Mist","description":"mist","icon":"50n"}]},{"id":2644688,"name":"Leeds","coord":{"lon":-1.54785,"lat":53.796478},"main":{"temp":1.28,"pressure":996,"temp_min":-1,"temp_max":5,"humidity":92},"dt":1479679848,"wind":{"speed":2.6,"deg":360},"clouds":{"all":0},"weather":[{"id":701,"main":"Mist","description":"mist","icon":"50n"}]},{"id":2657832,"name":"Aberdeen","coord":{"lon":-2.09814,"lat":57.143688},"main":{"temp":-2,"pressure":997,"humidity":86,"temp_min":-2,"temp_max":-2},"dt":1479683096,"wind":{"speed":2.6,"deg":260},"clouds":{"all":0},"weather":[{"id":800,"main":"Clear","description":"Sky is Clear","icon":"01n"}]},{"id":2641181,"name":"Norwich","coord":{"lon":1.29834,"lat":52.627831},"main":{"temp":5.28,"pressure":996,"humidity":100,"temp_min":5,"temp_max":6},"dt":1479679848,"wind":{"speed":1.5,"deg":210},"clouds":{"all":90},"weather":[{"id":701,"main":"Mist","description":"mist","icon":"50n"}]}]}